qtv/__init__.py
qtv-0.0.1.dist-info/LICENSE
qtv-0.0.1.dist-info/METADATA
qtv-0.0.1.dist-info/WHEEL
qtv-0.0.1.dist-info/top_level.txt
qtv-0.0.1.dist-info/RECORD
